carnotpy.py
carnotpy-0.9.0.dist-info/METADATA
carnotpy-0.9.0.dist-info/WHEEL
carnotpy-0.9.0.dist-info/top_level.txt
carnotpy-0.9.0.dist-info/RECORD
