Metadata-Version: 2.1
Name: carnotpy
Version: 0.9.0
Summary: Carnot Connection as a Python Package
Author: Carnot Innovations
Requires-Dist: pandas
Requires-Dist: requests
Requires-Dist: python-dateutil
